oka/__init__.py
oka/client.py
oka/config.py
oka-0.211211.2.dist-info/LICENSE
oka-0.211211.2.dist-info/WHEEL
oka-0.211211.2.dist-info/METADATA
oka-0.211211.2.dist-info/RECORD
