Metadata-Version: 2.1
Name: oka
Version: 0.211211.2
Summary: Python client for oka repository
License: GPL3
Author: Rafael Bizao
Author-email: rabizao@gmail.com
Requires-Python: >=3.8,<4.0
Classifier: License :: Other/Proprietary License
Classifier: Programming Language :: Python :: 3
Classifier: Programming Language :: Python :: 3.8
Classifier: Programming Language :: Python :: 3.9
Requires-Dist: PyJWT (>=2.3.0,<3.0.0)
Requires-Dist: SQLAlchemy (>=1.4.27,<2.0.0)
Requires-Dist: arff2pandas (==1.0.1)
Requires-Dist: idict (>=3.211211.2,<4.0.0)
Requires-Dist: pandas (==1.3.4)
Requires-Dist: python-dotenv (>=0.19.2,<0.20.0)
Requires-Dist: requests (>=2.26.0,<3.0.0)
Requires-Dist: scikit-learn (==1.0.1)
